README.txt
Receiver.py
Repeat.py
Sender.py
StorageMongoDB.py
receive2.py
send.py
setup.py
SuperMS.egg-info/PKG-INFO
SuperMS.egg-info/SOURCES.txt
SuperMS.egg-info/dependency_links.txt
SuperMS.egg-info/requires.txt
SuperMS.egg-info/top_level.txt
tools/__init__.py
tools/getmetrics.py
tools/imports.py