Metadata-Version: 1.0
Name: SuperMS
Version: 0.1
Summary: Supercalifragilisticexpialidocius Monitoring System project
Home-page: https://github.com/daniel00oo/CloudBaseSMS
Author: Daniel Herkel
Author-email: UNKNOWN
License: UNKNOWN
Platform: UNKNOWN
